pgc_finder/__init__.py
pgc_finder/_accessory.py
pgc_finder/_blast.py
pgc_finder/_cluster.py
pgc_finder/_count.py
pgc_finder/_parse.py
pgc_finder/_profile.py
pgc_finder/_search.py
pgc_finder/_seqlib.py
pgc_finder/_target.py
pgc_finder/_utils.py
pgc_finder/_visualize.py
pgc_finder/cli.py
pgc_finder/main.py
pgc_finder-0.0.4.dist-info/METADATA
pgc_finder-0.0.4.dist-info/WHEEL
pgc_finder-0.0.4.dist-info/entry_points.txt
pgc_finder-0.0.4.dist-info/top_level.txt
pgc_finder-0.0.4.dist-info/RECORD
