Metadata-Version: 2.1
Name: pgc-finder
Version: 0.0.4
Summary: Python package for probe-based gene cluster finding in large microbial genome database
Home-page: https://github.com/jrim42/pgc-finder
Author: jsrim
Author-email: comfortindex@naver.com
Keywords: gene,cluster,genomics,bioinformatics
Classifier: Programming Language :: Python :: 3.6
Classifier: Programming Language :: Python :: 3.7
Classifier: Programming Language :: Python :: 3.8
Classifier: Programming Language :: Python :: 3.9
Classifier: Programming Language :: Python :: 3.10
Classifier: Programming Language :: Python :: 3.11
Requires-Python: >=3.6
Requires-Dist: pandas
Requires-Dist: matplotlib
Requires-Dist: requests
